setup.py
bn_gs_prob_dist/Binomialdistribution.py
bn_gs_prob_dist/Gaussiandistribution.py
bn_gs_prob_dist/Generaldistribution.py
bn_gs_prob_dist/__init__.py
bn_gs_prob_dist.egg-info/PKG-INFO
bn_gs_prob_dist.egg-info/SOURCES.txt
bn_gs_prob_dist.egg-info/dependency_links.txt
bn_gs_prob_dist.egg-info/not-zip-safe
bn_gs_prob_dist.egg-info/top_level.txt