Metadata-Version: 1.0
Name: bn-gs-prob-dist
Version: 1.0
Summary: Binomial & gaussian distributions
Home-page: UNKNOWN
Author: Shaun Cox
Author-email: shaun@something.com
License: UNKNOWN
Platform: UNKNOWN
